opnieuw/__init__.py
opnieuw/clock.py
opnieuw/exceptions.py
opnieuw/py.typed
opnieuw/retries.py
opnieuw/test_util.py
opnieuw/util.py
opnieuw-3.3.0.dist-info/licenses/LICENSE
opnieuw-3.3.0.dist-info/METADATA
opnieuw-3.3.0.dist-info/WHEEL
opnieuw-3.3.0.dist-info/top_level.txt
opnieuw-3.3.0.dist-info/RECORD
